ap_test_project_251219v3/__init__.py
ap_test_project_251219v3-0.1.0.dist-info/METADATA
ap_test_project_251219v3-0.1.0.dist-info/WHEEL
ap_test_project_251219v3-0.1.0.dist-info/entry_points.txt
ap_test_project_251219v3-0.1.0.dist-info/licenses/LICENSE
ap_test_project_251219v3-0.1.0.dist-info/RECORD
