Metadata-Version: 2.4
Name: ap-test-project-251219v3
Version: 0.1.0
Summary: A short description of the project
License-File: LICENSE
Author: Antonio Pisani
Author-email: antonio.pisani@gmail.com
Requires-Python: >=3.10
Classifier: Programming Language :: Python :: 3
Classifier: Programming Language :: Python :: 3.10
Classifier: Programming Language :: Python :: 3.11
Classifier: Programming Language :: Python :: 3.12
Classifier: Programming Language :: Python :: 3.13
Classifier: Programming Language :: Python :: 3.14
Project-URL: Documentation, https://ap-test-project-251219v3.readthedocs.io/
Project-URL: Issue Tracker, https://github.com/apisani1/ap-test-project-251219v3/issues
Project-URL: Release Notes, https://github.com/apisani1/ap-test-project-251219v3/releases
Project-URL: Source Code, https://github.com/apisani1/ap-test-project-251219v3
